epy_reader/__init__.py
epy_reader/__main__.py
epy_reader/board.py
epy_reader/cli.py
epy_reader/config.py
epy_reader/ebooks/__init__.py
epy_reader/ebooks/azw.py
epy_reader/ebooks/base.py
epy_reader/ebooks/epub.py
epy_reader/ebooks/fictionbook.py
epy_reader/ebooks/mobi.py
epy_reader/ebooks/url.py
epy_reader/lib.py
epy_reader/models.py
epy_reader/parser.py
epy_reader/reader.py
epy_reader/settings.py
epy_reader/speakers/__init__.py
epy_reader/speakers/base.py
epy_reader/speakers/gtts_mpv.py
epy_reader/speakers/mimic.py
epy_reader/speakers/pico.py
epy_reader/state.py
epy_reader/tools/KindleUnpack/__init__.py
epy_reader/tools/KindleUnpack/compatibility_utils.py
epy_reader/tools/KindleUnpack/kindleunpack.py
epy_reader/tools/KindleUnpack/mobi_cover.py
epy_reader/tools/KindleUnpack/mobi_dict.py
epy_reader/tools/KindleUnpack/mobi_header.py
epy_reader/tools/KindleUnpack/mobi_html.py
epy_reader/tools/KindleUnpack/mobi_index.py
epy_reader/tools/KindleUnpack/mobi_k8proc.py
epy_reader/tools/KindleUnpack/mobi_k8resc.py
epy_reader/tools/KindleUnpack/mobi_nav.py
epy_reader/tools/KindleUnpack/mobi_ncx.py
epy_reader/tools/KindleUnpack/mobi_opf.py
epy_reader/tools/KindleUnpack/mobi_pagemap.py
epy_reader/tools/KindleUnpack/mobi_sectioner.py
epy_reader/tools/KindleUnpack/mobi_split.py
epy_reader/tools/KindleUnpack/mobi_uncompress.py
epy_reader/tools/KindleUnpack/mobi_utils.py
epy_reader/tools/KindleUnpack/mobiml2xhtml.py
epy_reader/tools/KindleUnpack/unipath.py
epy_reader/tools/KindleUnpack/unpack_structure.py
epy_reader/tools/__init__.py
epy_reader/utils.py
epy_reader-2023.6.11.dist-info/entry_points.txt
epy_reader-2023.6.11.dist-info/LICENSE
epy_reader-2023.6.11.dist-info/WHEEL
epy_reader-2023.6.11.dist-info/METADATA
epy_reader-2023.6.11.dist-info/RECORD
