Metadata-Version: 2.1
Name: epy-reader
Version: 2023.6.11
Summary: TUI Ebook Reader
Home-page: https://github.com/wustho/epy
License: GPL-3.0
Keywords: ebook,epub,epub3,fb2,mobi,azw3,TUI,ebook reader
Author: Benawi Adha
Author-email: benawiadha@gmail.com
Requires-Python: >=3.8,<4.0
Classifier: License :: OSI Approved :: GNU General Public License v3 (GPLv3)
Classifier: Programming Language :: Python :: 3
Classifier: Programming Language :: Python :: 3.8
Classifier: Programming Language :: Python :: 3.9
Classifier: Programming Language :: Python :: 3.10
Classifier: Programming Language :: Python :: 3.11
Requires-Dist: windows-curses; platform_system == "Windows"
Project-URL: Repository, https://github.com/wustho/epy
